{
  "settings": {
    "startDate": "2026-06-07"
  },
  "daily": {
    "2026-06-07": {
      "studyHours": "3.5",
      "topics": "",
      "lcEasy": "1",
      "lcMed": "1",
      "lcHard": "1",
      "projectHours": "0",
      "mainTopic": "DSA/LeetCode",
      "sleep": "7",
      "water": "8",
      "energy": "7",
      "focus": "7",
      "confidence": "7",
      "gym": true,
      "meditation": true,
      "wins": "hi",
      "challenges": "bye",
      "tomorrow": "123",
      "timestamp": "2026-06-08T00:19:10.521Z"
    },
    "2026-06-13": {
      "studyHours": "0",
      "topics": "",
      "lcEasy": "0",
      "lcMed": "0",
      "lcHard": "0",
      "projectHours": "0",
      "mainTopic": "",
      "sleep": "7",
      "water": "8",
      "energy": "7",
      "focus": "7",
      "confidence": "7",
      "gym": false,
      "meditation": false,
      "wins": "",
      "challenges": "",
      "tomorrow": "",
      "timestamp": "2026-06-13T22:04:22.249Z"
    }
  },
  "roadmap": {
    "dsa": {
      "checklist": {
        "1": false,
        "2": false,
        "3": false,
        "4": false,
        "5": false,
        "6": false,
        "7": false,
        "8": false,
        "9": false,
        "10": false
      },
      "lastRevision": "2026-06-07T16:24:25.184Z",
      "mastery": "25",
      "confidence": "13",
      "notes": "This is in the DSA"
    },
    "system_design": {
      "checklist": {
        "1": false,
        "2": true,
        "3": true,
        "4": false,
        "5": false,
        "7": false,
        "8": false,
        "9": true,
        "10": false,
        "12": false,
        "13": false,
        "14": false,
        "15": false,
        "16": false,
        "18": false,
        "19": false,
        "20": false,
        "21": false,
        "22": false,
        "23": false,
        "25": false,
        "26": false,
        "27": false,
        "28": false,
        "30": false,
        "31": false,
        "32": false,
        "33": false,
        "34": false,
        "35": false,
        "36": false,
        "37": false,
        "38": false,
        "39": false,
        "40": false,
        "41": false,
        "42": false,
        "43": false,
        "45": false,
        "46": false,
        "47": false,
        "48": false,
        "49": false,
        "51": false,
        "52": false,
        "53": false,
        "54": false,
        "55": false,
        "56": false,
        "58": false,
        "59": false,
        "60": false,
        "61": false,
        "62": false
      },
      "mastery": "9",
      "confidence": "12",
      "notes": "This note is for System Design"
    },
    "springboot": {
      "checklist": {}
    },
    "distributed": {
      "checklist": {}
    }
  },
  "projects": null,
  "interview": {
    "dsa": {
      "d1": {
        "status": "todo",
        "notes": "This is a Two Sum Problem"
      },
      "d2": {
        "status": "todo"
      },
      "d3": {
        "status": "todo"
      },
      "d11": {
        "status": "todo"
      },
      "d12": {
        "status": "todo"
      },
      "d13": {
        "status": "todo"
      },
      "d14": {
        "status": "todo"
      },
      "d15": {
        "status": "todo"
      },
      "d16": {
        "status": "todo"
      },
      "d26": {
        "status": "todo"
      }
    },
    "sysdesign": {
      "sd11": {
        "status": "todo"
      },
      "sd1": {
        "status": "todo",
        "approach": "Real-time messaging system for 2B+ users"
      },
      "sd2": {
        "status": "todo"
      }
    },
    "behavioral": {
      "bh1": {
        "status": "todo"
      },
      "bh5": {
        "status": "todo"
      }
    },
    "sql": {
      "sq1": {
        "status": "todo",
        "notes": "Combining rows from multiple tables using relational keys"
      },
      "sq2": {
        "status": "todo"
      }
    },
    "java": {
      "j1": {
        "status": "todo"
      }
    }
  },
  "flashcards": [
    {
      "id": "fc_1780815891842",
      "front": "test",
      "back": "test",
      "category": "DSA",
      "created": "2026-06-07T07:04:51.842Z",
      "nextReview": "2026-06-25T22:05:27.883Z",
      "interval": 18,
      "easeFactor": 2.5,
      "reviews": 10,
      "correct": 6
    }
  ],
  "notes": [],
  "weekly": {
    "2026-06-01": {
      "goals": {
        "hours": "28",
        "lc": "15",
        "gym": "6",
        "meditation": "7",
        "topics": ""
      },
      "review": {
        "wins": "Hi",
        "improve": "Bye",
        "nextPriorities": "1,,2,3"
      }
    },
    "2026-06-08": {
      "goals": {
        "hours": "28",
        "lc": "15",
        "gym": "5",
        "meditation": "5",
        "topics": ""
      },
      "review": {
        "wins": "",
        "improve": "",
        "nextPriorities": ""
      }
    }
  }
}